{
    "data": [
        {
            "url": "https://images.unsplash.com/photo-1604223190546-a43e4c7f29d7?q=80&w=2069",
            "fileName": "mountain_landscape.jpg",
            "altText": "A scenic mountain landscape with a clear blue sky."
        },
        {
            "url": "https://w.wallhaven.cc/full/nk/wallhaven-nkgwm4.jpg",
            "fileName": "city_night.png",
            "altText": "A bustling city street at night with bright lights."
        },
        {
            "url": "https://w.wallhaven.cc/full/w8/wallhaven-w8lwyr.jpg",
            "fileName": "beach_sunset.jpeg",
            "altText": "A beautiful sunset over a calm beach with gentle waves."
        },
        {
            "url": "https://w.wallhaven.cc/full/6q/wallhaven-6qm8o6.jpg",
            "fileName": "forest_path.gif",
            "altText": "A winding path through a dense forest with tall trees."
        },
        {
            "url": "https://w.wallhaven.cc/full/eo/wallhaven-eo5g6l.jpg",
            "fileName": "abstract_art.webp",
            "altText": "An abstract art piece with vibrant colors and shapes."
        },
        {
            "url": "https://example.com/images/puppy_play.jpg",
            "fileName": "puppy_play.jpg",
            "altText": "A golden retriever puppy playing in a field of grass."
        },
        {
            "url": "https://w.wallhaven.cc/full/mp/wallhaven-mpqdp9.jpg",
            "fileName": "coffee_cup.png",
            "altText": "A steaming cup of coffee on a wooden table."
        },
        {
            "url": "https://w.wallhaven.cc/full/mp/wallhaven-mpzx71.jpg",
            "fileName": "space_nebula.jpeg",
            "altText": "A colorful nebula in deep space with stars and gas clouds."
        },
        {
            "url": "https://w.wallhaven.cc/full/45/wallhaven-45d188.jpg",
            "fileName": "old_book.gif",
            "altText": "A close up of an old book with aged pages."
        },
        {
            "url": "https://w.wallhaven.cc/full/qd/wallhaven-qdq58r.jpg",
            "fileName": "modern_building.webp",
            "altText": "A tall modern building with glass windows reflecting the sky."
        }
    ]
}